django_srcdoc/__about__.py
django_srcdoc/__init__.py
django_srcdoc/templatetags/srcdoc.py
django_srcdoc-1.0.1.dist-info/METADATA
django_srcdoc-1.0.1.dist-info/WHEEL
django_srcdoc-1.0.1.dist-info/licenses/LICENSE
django_srcdoc-1.0.1.dist-info/RECORD
