Metadata-Version: 2.3
Name: django-srcdoc
Version: 1.0.1
Summary: A simple Django template tag to automate escaping HTML for use with the iframe srcdoc attribute. 
Project-URL: Documentation, https://github.com/sheepman4267/django-srcdoc#readme
Project-URL: Issues, https://github.com/sheepman4267/django-srcdoc/issues
Project-URL: Source, https://github.com/sheepman4267/django-srcdoc
Author-email: Hans Kelson <hans@communitycomputing.net>
License-Expression: MIT
License-File: LICENSE
Classifier: Development Status :: 5 - Production/Stable
Classifier: Framework :: Django
Classifier: Framework :: Django :: 5.0
Classifier: Framework :: Django :: 5.1
Classifier: Programming Language :: Python
Classifier: Programming Language :: Python :: 3.10
Classifier: Programming Language :: Python :: 3.11
Classifier: Programming Language :: Python :: 3.12
Classifier: Programming Language :: Python :: Implementation :: CPython
Classifier: Programming Language :: Python :: Implementation :: PyPy
Requires-Python: >=3.10
Requires-Dist: django<5.2,>=5.1
